CHANGELOG.md
LICENSE
MANIFEST.in
README.md
RELEASE.md
install.json
package.json
pyproject.toml
setup.py
tsconfig.json
yarn.lock
jupyterlab_markdownit/__init__.py
jupyterlab_markdownit/_version.py
jupyterlab_markdownit.egg-info/PKG-INFO
jupyterlab_markdownit.egg-info/SOURCES.txt
jupyterlab_markdownit.egg-info/dependency_links.txt
jupyterlab_markdownit.egg-info/not-zip-safe
jupyterlab_markdownit.egg-info/top_level.txt
jupyterlab_markdownit/labextension/build_log.json
jupyterlab_markdownit/labextension/package.json
jupyterlab_markdownit/labextension/schemas/jupyterlab-markdownit/core.json
jupyterlab_markdownit/labextension/schemas/jupyterlab-markdownit/package.json.orig
jupyterlab_markdownit/labextension/static/lib_index_js.6902f59d9c7e8720f139.js
jupyterlab_markdownit/labextension/static/lib_index_js.6902f59d9c7e8720f139.js.map
jupyterlab_markdownit/labextension/static/node_modules_markdown-it-task-checkbox_index_js.57898041b85d8a36c0d4.js
jupyterlab_markdownit/labextension/static/node_modules_markdown-it-task-checkbox_index_js.57898041b85d8a36c0d4.js.map
jupyterlab_markdownit/labextension/static/remoteEntry.44e18bec2e3976cebfa2.js
jupyterlab_markdownit/labextension/static/remoteEntry.44e18bec2e3976cebfa2.js.map
jupyterlab_markdownit/labextension/static/style.js
jupyterlab_markdownit/labextension/static/style_index_js.24cc5e2dcfa2c4f3f94c.js
jupyterlab_markdownit/labextension/static/style_index_js.24cc5e2dcfa2c4f3f94c.js.map
jupyterlab_markdownit/labextension/static/vendors-node_modules_markdown-it-anchor_dist_markdownItAnchor_mjs.22ef9ca33c024ba278bb.js
jupyterlab_markdownit/labextension/static/vendors-node_modules_markdown-it-anchor_dist_markdownItAnchor_mjs.22ef9ca33c024ba278bb.js.map
jupyterlab_markdownit/labextension/static/vendors-node_modules_markdown-it-diagrams_lib_index_js.55affff2ec1677d752e5.js
jupyterlab_markdownit/labextension/static/vendors-node_modules_markdown-it-diagrams_lib_index_js.55affff2ec1677d752e5.js.map
jupyterlab_markdownit/labextension/static/vendors-node_modules_markdown-it-docutils_dist_css_style_min_css.47d0c11f951a83d36cbb.js
